slima2a/__init__.py
slima2a/client_transport.py
slima2a/handler.py
slima2a/py.typed
slima2a/types/__init__.py
slima2a/types/a2a_pb2_slimrpc.py
slima2a-0.2.2.dist-info/METADATA
slima2a-0.2.2.dist-info/WHEEL
slima2a-0.2.2.dist-info/RECORD
