Metadata-Version: 2.4
Name: slima2a
Version: 0.2.2
Summary: A2A protocol over slimrpc
Project-URL: Repository, https://github.com/agntcy/slim
Project-URL: Issues, https://github.com/agntcy/slim/issues
Project-URL: Changelog, https://github.com/agntcy/slim/blob/main/data-plane/python/integrations/slima2a/CHANGELOG.md
Classifier: Development Status :: 3 - Alpha
Classifier: Intended Audience :: Developers
Classifier: Programming Language :: Python :: 3.10
Classifier: Programming Language :: Python :: 3.11
Classifier: Programming Language :: Python :: 3.12
Classifier: Programming Language :: Python :: 3.13
Classifier: Topic :: Software Development :: Libraries
Requires-Python: <4.0,>=3.10
Requires-Dist: a2a-sdk[telemetry]==0.3.20
Requires-Dist: slimrpc~=0.2.0
